CHANGES.txt
CONTRIBUTORS.txt
MANIFEST.in
README.txt
development.ini
development_agent.ini
i18n.ini
production.ini
setup.cfg
setup.py
PubliForge.egg-info/PKG-INFO
PubliForge.egg-info/SOURCES.txt
PubliForge.egg-info/dependency_links.txt
PubliForge.egg-info/entry_points.txt
PubliForge.egg-info/not-zip-safe
PubliForge.egg-info/requires.txt
PubliForge.egg-info/top_level.txt
publiforge/__init__.py
publiforge/initialize.py
publiforge/Locale/publiforge.pot
publiforge/Locale/es/LC_MESSAGES/publiforge.mo
publiforge/Locale/es/LC_MESSAGES/publiforge.po
publiforge/Locale/fr/LC_MESSAGES/colander.mo
publiforge/Locale/fr/LC_MESSAGES/colander.po
publiforge/Locale/fr/LC_MESSAGES/publiforge.mo
publiforge/Locale/fr/LC_MESSAGES/publiforge.po
publiforge/Openers/Image/image.ini
publiforge/Openers/Image/opener.xml
publiforge/Openers/ImageEdit/image.ini
publiforge/Openers/ImageEdit/opener.xml
publiforge/Openers/Ini/ini.ini
publiforge/Openers/Ini/opener.xml
publiforge/Openers/NoMore/opener.xml
publiforge/Openers/Plain/opener.xml
publiforge/Openers/Publidoc/opener.xml
publiforge/Openers/Publidoc/xml.ini
publiforge/Openers/Publidoc/Maestro/publidoc_render4maestro.xsl
publiforge/Openers/Publidoc/Maestro/publidoc_xml4maestro.xsl
publiforge/Openers/Publidoc/Regex/publidoc_save.regex
publiforge/Openers/Publidoc/Seeds/publidoc_document.xml
publiforge/Openers/Publidoc/Seeds/publidoc_glossary.xml
publiforge/Openers/Publidoc/Seeds/publidoc_topic.xml
publiforge/Openers/Publidoc/Static/Css/publidoc_opener.css
publiforge/Openers/Publidoc/Static/Css/publidoc_schema.css
publiforge/Openers/Publidoc/Static/Js/codemirror4publidoc_loader.js
publiforge/Openers/Publidoc/Static/Js/publidoc_schema.js
publiforge/Openers/Publidoc/Variables/publidoc.pfvar.xml
publiforge/Openers/Publidoc/Xsl/publidoc_edit.xsl
publiforge/Openers/Publidoc/Xsl/publidoc_edit_base.inc.xsl
publiforge/Openers/Publidoc/Xsl/publidoc_overview.xsl
publiforge/Openers/Publidoc/Xsl/publidoc_render.xsl
publiforge/Openers/Publidoc/Xsl/publidoc_save.xsl
publiforge/Openers/Publidoc/Xsl/publidoc_save_base.inc.xsl
publiforge/Openers/Publiquiz/opener.xml
publiforge/Openers/Publiquiz/xml.ini
publiforge/Openers/Publiquiz/Regex/publiquiz_save.regex
