Metadata-Version: 2.1
Name: PubliForge
Version: 2.2
Summary: Online multimedia publishing system
Home-page: http://docs.publiforge.org
Author: Patrick PIERRE
Author-email: patrick.pierre@lap2.fr
License: UNKNOWN
Keywords: web wsgi bfg pylons pyramid publiforge
Platform: UNKNOWN
Classifier: Programming Language :: Python
Classifier: Programming Language :: Python :: 2
Classifier: Programming Language :: Python :: 2.7
Classifier: Framework :: Pyramid
Classifier: Topic :: Internet :: WWW/HTTP
Classifier: Topic :: Internet :: WWW/HTTP :: WSGI :: Application
Provides-Extra: development
Provides-Extra: testing
Provides-Extra: documentation
